README.md
setup.cfg
setup.py
e2eakarev/__init__.py
e2eakarev.egg-info/PKG-INFO
e2eakarev.egg-info/SOURCES.txt
e2eakarev.egg-info/dependency_links.txt
e2eakarev.egg-info/requires.txt
e2eakarev.egg-info/top_level.txt